repelsec/__init__.py
repelsec/cpe_dictionary.json
repelsec/cwe_vulnerabilities.py
repelsec/functions.py
repelsec/generate_pdf.py
repelsec/main.py
repelsec/tests.py
repelsec/unit_tests.py
repelsec-1.0.dist-info/LICENSE
repelsec-1.0.dist-info/METADATA
repelsec-1.0.dist-info/WHEEL
repelsec-1.0.dist-info/entry_points.txt
repelsec-1.0.dist-info/top_level.txt
repelsec-1.0.dist-info/RECORD
