Metadata-Version: 2.1
Name: repelsec
Version: 1.0
License-File: LICENSE
Requires-Dist: nvdlib ~=0.7.7
Requires-Dist: xmltodict ~=0.13.0
Requires-Dist: pandas ~=2.1.4
Requires-Dist: argparse ~=1.4.0
Requires-Dist: setuptools ~=69.0.3
Requires-Dist: fpdf ~=1.7.2
Requires-Dist: PyPDF2 ~=3.0.1
Requires-Dist: requests ~=2.31.0
